{
  "week_start": "2026-04-19",
  "days": {
    "2026-04-19": {
      "Adham": "WFO",
      "Karam": "WFH",
      "Abdelkhalek": "WFO",
      "Hesham": "WFH",
      "Salma": "WFH"
    },
    "2026-04-20": {
      "Adham": "WFO",
      "Karam": "WFO",
      "Abdelkhalek": "WFH",
      "Hesham": "WFH",
      "Salma": "WFO"
    },
    "2026-04-21": {
      "Adham": "WFH",
      "Karam": "WFO",
      "Abdelkhalek": "WFH",
      "Hesham": "WFO",
      "Salma": "WFO"
    },
    "2026-04-22": {
      "Adham": "WFH",
      "Karam": "WFH",
      "Abdelkhalek": "WFO",
      "Hesham": "WFO",
      "Salma": "WFH"
    },
    "2026-04-23": {
      "Adham": "WFO",
      "Karam": "WFO",
      "Abdelkhalek": "WFO",
      "Hesham": "WFH",
      "Salma": "WFH"
    }
  }
}